setup.py
commonslib/__init__.py
commonslib/biz_model.py
commonslib/database.py
commonslib/database_factory.py
commonslib/database_mixin.py
commonslib/dateutil.py
commonslib/decoraters_tornado.py
commonslib/fileutil.py
commonslib/imageprocessor.py
commonslib/jsonutil.py
commonslib/megaboat.py
commonslib/memcache_factory.py
commonslib/network.py
commonslib/oss_factory.py
commonslib/stringutil.py
commonslib/thrift_factory.py
commonslib/validators.py
commonslib/view_model.py
commonslibs.egg-info/PKG-INFO
commonslibs.egg-info/SOURCES.txt
commonslibs.egg-info/dependency_links.txt
commonslibs.egg-info/top_level.txt