Metadata-Version: 1.0
Name: commonslibs
Version: 0.0.1
Summary: zhaowenlei upload commonslibs
Home-page: http://liluo.org
Author: liluo
Author-email: zhaowenlei789@sina.com
License: MIT License
Keywords: commonslib,commonslibs
Platform: any
